{
  "ru": {
    "create_program": "Cоздал программу:",
    "intro": "и ООО \"Пельманая хоприка\"",
    "welcome": "Здравствуйте, вы в редакторе фотографии.",
    "choice_photo": "Выберите картинку",
    "choice_photo_give": "Вы выбрали фотографию по пути: %s",
    "choice_sure": "Вы уверены с выбором? да/нет\n",
    "mode_choice": "Выберите режим\n1) Мем режим\n2) Фото режим\n3) Всеобщий режим\n4) Выйти из программы",
    "meme_mode": "Выберите фильтр\n1) Текст\n2) Дед инсайд\n3) Барби\n4) Сшакалить качество",
    "photo_mode": "Выберите фильтр\n1) Блюр\n2) Инверсия\n3) Клетки",
    "all_mode": "Выберите фильтр\n1) Текст\n2) Дед инсайд\n3) Барби\n4) Сшакалить качество\n5) Блюр\n6) Инверсия\n7) Клетки",
    "exit_mode": "%s) Выйти из режима",
    "description_filter": "этот фильтр делает: ",
    "menu_img": "Выберите:\n1) Показать изображение\n2) Сохранить\n3) Продолжить",
    "desc_text": "Добавляет текст на изображение",
    "desc_ded_inside": "Делает изображение черно белым",
    "desc_barbi": "Делает картинку в розовых тонах",
    "desc_shukal": "Делает разрешение картинки супер плохим",
    "desc_blur": "Делает размытие на картинке",
    "desc_inversion": "Делает инверсию",
    "desc_kletki": "Делает инверсию через каждый пиксель",
    "text_write": "Напишите текст:",
    "blur_stroung": "Укажите силу брюра: ",
    "error": "Ошибка, попробуйте еще раз"
  },
  "en": {
    "create_program": "create program:",
    "intro": "and LLC \"dumplings hoprik`s\"",
    "welcome": "Hello, you are in the photo editor.",
    "choice_photo": "Choose a picture",
    "choice_photo_give": "You have chosen a photo along the path: %s",
    "choice_sure": "Are you sure about the choice? yes/no\n",
    "mode_choice": "Choose mode\n1) Meme mode\n2) Photo mode\n3) General mode\n4) Exit the program",
    "meme_mode": "Choose a filter\n1) Text\n2) Grandpa Inside\n3) Barbie\n4) Shakalify quality",
    "photo_mode": "Choose a filter\n1) Blur\n2) Inversion\n3) Cells",
    "all_mode": "Choose a filter\n1) Text\n2) Grandpa Inside\n3) Barbie\n4) Shakalify quality\n5) Blur\n6) Inversion\n7) Cells",
    "exit_mode": "%s) Exit the mode",
    "description_filter": "this filter does: ",
    "menu_img": "Choose:\n1) Show image\n2) Save\n3) Continue",
    "desc_text": "Adds text to the image",
    "desc_ded_inside": "Turns the image black and white",
    "desc_barbi": "Gives the picture a pinkish tone",
    "desc_shukal": "Makes the image resolution extremely poor",
    "desc_blur": "Applies blurring to the image",
    "desc_inversion": "Applies inversion",
    "desc_kletki": "Applies inversion through each pixel",
    "text_write": "Write text: ",
    "blur_stroung": "Specify blur strength: ",
    "error": "Error, please try again"
  }
}